[
     {
      "id": "9fa8d860-329d-4e16-b0bb-93783d583174",
      "name": "Liam",
      "surname": "Nuske",
      "email": "liamnuske@gmail.com",
      "password": "$2a$10$.o7oNKHrKXsBUynpqLKC8.rISljFXVrZN/OFPr1fkOiV8q2EhSnem",
      "rol": "user",
      "telefono": null,
      "genero": null,
      "asiento": null,
      "suscripcion": null,
      "fotoPerfil": null,
      "birthday": null
   },
   {
      "id": "816c2f17-f6b3-4fec-be9c-69694ef21a94",
      "name": "Leo",
      "surname": "Nuske",
      "email": "leonuske2@gmail.com",
      "password": "$2a$10$cQvedGDSQfnnlZSaGkYNwOfSoMCJkoVz7KVI4yKJIWk3YdbpzGYqS",
      "rol": "admin",
      "telefono": null,
      "genero": null,
      "asiento": null,
      "suscripcion": null,
      "fotoPerfil": null,
      "birthday": null
   },
   {
      "id": "911f75f9-b226-4496-b628-f58df998c535",
      "name": "cindy",
      "surname": "nunske",
      "email": "cindynuske@gmail.com",
      "password": "$2a$10$U/tlij0PL6xcudgkRrAQweHNK83AW5CiTQeBqoQpcU/rcbK9UuV5K",
      "rol": "user",
      "telefono": null,
      "genero": null,
      "asiento": null,
      "suscripcion": null,
      "fotoPerfil": null,
      "birthday": null
   },
   {
      "id": "546f5a33-1e0c-425b-a5eb-39c0e4a887f0",
      "name": "Clara",
      "surname": "Zalazar",
      "email": "clarazalazar@gmail.com",
      "password": "$2a$10$Y/pM0ltIQnxowMnZjH5wguzwEoNyRwoK5G9TCS3v7m93UpVc7.sFW",
      "rol": "admin",
      "telefono": null,
      "genero": null,
      "asiento": null,
      "suscripcion": null,
      "fotoPerfil": null,
      "birthday": null
   }
]